nomad_simulations/__init__.py
nomad_simulations/_version.py
nomad_simulations/schema_packages/__init__.py
nomad_simulations/schema_packages/atoms_state.py
nomad_simulations/schema_packages/basis_set.py
nomad_simulations/schema_packages/common.py
nomad_simulations/schema_packages/data_types.py
nomad_simulations/schema_packages/force_field.py
nomad_simulations/schema_packages/general.py
nomad_simulations/schema_packages/model_method.py
nomad_simulations/schema_packages/model_system.py
nomad_simulations/schema_packages/numerical_settings.py
nomad_simulations/schema_packages/outputs.py
nomad_simulations/schema_packages/physical_property.py
nomad_simulations/schema_packages/variables.py
nomad_simulations/schema_packages/properties/__init__.py
nomad_simulations/schema_packages/properties/band_gap.py
nomad_simulations/schema_packages/properties/band_structure.py
nomad_simulations/schema_packages/properties/energies.py
nomad_simulations/schema_packages/properties/fermi_surface.py
nomad_simulations/schema_packages/properties/forces.py
nomad_simulations/schema_packages/properties/greens_function.py
nomad_simulations/schema_packages/properties/hopping_matrix.py
nomad_simulations/schema_packages/properties/permittivity.py
nomad_simulations/schema_packages/properties/spectral_profile.py
nomad_simulations/schema_packages/properties/thermodynamics.py
nomad_simulations/schema_packages/utils/__init__.py
nomad_simulations/schema_packages/utils/utils.py
nomad_simulations/schema_packages/workflow/__init__.py
nomad_simulations/schema_packages/workflow/beyond_dft.py
nomad_simulations/schema_packages/workflow/dmft.py
nomad_simulations/schema_packages/workflow/elastic.py
nomad_simulations/schema_packages/workflow/equation_of_state.py
nomad_simulations/schema_packages/workflow/general.py
nomad_simulations/schema_packages/workflow/geometry_optimization.py
nomad_simulations/schema_packages/workflow/gw.py
nomad_simulations/schema_packages/workflow/max_ent.py
nomad_simulations-0.5.0.dist-info/licenses/LICENSE
nomad_simulations-0.5.0.dist-info/METADATA
nomad_simulations-0.5.0.dist-info/WHEEL
nomad_simulations-0.5.0.dist-info/entry_points.txt
nomad_simulations-0.5.0.dist-info/top_level.txt
nomad_simulations-0.5.0.dist-info/RECORD
