Metadata-Version: 2.4
Name: nomad-simulations
Version: 0.5.0
Summary: A NOMAD plugin for FAIR schemas for simulation data.
Author-email: "Jose M. Pizarro" <jose.pizarro@physik.hu-berlin.de>, Nathan Daelman <ndaelman@physik.hu-berlin.de>, Bernadette Mohr <mohrbern@physik.hu-berlin.de>, "Joseph F. Rudzinski" <joseph.rudzinski@physik.hu-berlin.de>
Maintainer-email: "Jose M. Pizarro" <jose.pizarro@physik.hu-berlin.de>, "Joseph F. Rudzinski" <joseph.rudzinski@physik.hu-berlin.de>
License:                                  Apache License
Project-URL: Homepage, https://github.com/nomad-coe/nomad-simulations
Project-URL: Bug Tracker, https://github.com/nomad-coe/nomad-simulations/issues
Project-URL: Documentation, https://nomad-coe.github.io/nomad-simulations/
Classifier: Intended Audience :: Developers
Classifier: Operating System :: OS Independent
Classifier: Programming Language :: Python
Classifier: Programming Language :: Python :: 3.10
Classifier: Programming Language :: Python :: 3.11
Classifier: Programming Language :: Python :: 3.12
Classifier: License :: OSI Approved :: Apache Software License
Requires-Python: >=3.10
License-File: LICENSE
Requires-Dist: nomad-lab[infrastructure]>=1.3.15
Requires-Dist: matid>=2.0.0.dev2
Provides-Extra: dev
Requires-Dist: mypy>=1.15; extra == "dev"
Requires-Dist: pytest<8,>=5.3.0; extra == "dev"
Requires-Dist: pytest-timeout>=1.4.2; extra == "dev"
Requires-Dist: pytest-cov>=2.7.1; extra == "dev"
Requires-Dist: ruff>=0.6; extra == "dev"
Requires-Dist: structlog>=1.0; extra == "dev"
Requires-Dist: typing-extensions>=4.12; extra == "dev"
Dynamic: license-file
